geo_heatmap
